<annotation>
	<folder></folder>
	<filename>2Q-8-_jpg.rf.d7eb509a944e2ef5ae34563ee242966c.jpg</filename>
	<path>2Q-8-_jpg.rf.d7eb509a944e2ef5ae34563ee242966c.jpg</path>
	<source>
		<database>roboflow.com</database>
	</source>
	<size>
		<width>640</width>
		<height>640</height>
		<depth>3</depth>
	</size>
	<segmented>0</segmented>
	<object>
		<name>Abrador</name>
		<pose>Unspecified</pose>
		<truncated>0</truncated>
		<difficult>0</difficult>
		<occluded>0</occluded>
		<bndbox>
			<xmin>126</xmin>
			<xmax>393</xmax>
			<ymin>4</ymin>
			<ymax>308</ymax>
		</bndbox>
	</object>
	<object>
		<name>Abrador</name>
		<pose>Unspecified</pose>
		<truncated>0</truncated>
		<difficult>0</difficult>
		<occluded>0</occluded>
		<bndbox>
			<xmin>154</xmin>
			<xmax>415</xmax>
			<ymin>372</ymin>
			<ymax>640</ymax>
		</bndbox>
	</object>
	<metadata>
	</metadata>
</annotation>
