<annotation>
	<folder></folder>
	<filename>307_jpg.rf.45ae5d0ab51c8c82622da8fd4680f0cc.jpg</filename>
	<path>307_jpg.rf.45ae5d0ab51c8c82622da8fd4680f0cc.jpg</path>
	<source>
		<database>roboflow.com</database>
	</source>
	<size>
		<width>640</width>
		<height>640</height>
		<depth>3</depth>
	</size>
	<segmented>0</segmented>
	<object>
		<name>dog</name>
		<pose>Unspecified</pose>
		<truncated>0</truncated>
		<difficult>0</difficult>
		<occluded>0</occluded>
		<bndbox>
			<xmin>220</xmin>
			<xmax>329</xmax>
			<ymin>464</ymin>
			<ymax>640</ymax>
		</bndbox>
	</object>
	<metadata>
	</metadata>
</annotation>
