<annotation>
	<folder></folder>
	<filename>424_jpg.rf.3c46c02ba0bc7ff329dbec66293b498f.jpg</filename>
	<path>424_jpg.rf.3c46c02ba0bc7ff329dbec66293b498f.jpg</path>
	<source>
		<database>roboflow.com</database>
	</source>
	<size>
		<width>640</width>
		<height>640</height>
		<depth>3</depth>
	</size>
	<segmented>0</segmented>
	<object>
		<name>dog</name>
		<pose>Unspecified</pose>
		<truncated>0</truncated>
		<difficult>0</difficult>
		<occluded>0</occluded>
		<bndbox>
			<xmin>493</xmin>
			<xmax>563</xmax>
			<ymin>137</ymin>
			<ymax>235</ymax>
		</bndbox>
	</object>
	<metadata>
	</metadata>
</annotation>
